<?xml version="1.0" encoding="utf-8"?>
<OrleansConfiguration xmlns="urn:orleans">
  <Globals>
    <SeedNode Address="localhost" Port="11111" />
    <ReminderService ReminderServiceType="ReminderTableGrain" />
    <StorageProviders>
      <Provider Type="Orleans.Storage.MemoryStorage" Name="Default" />
      <Provider Type="Orleans.Storage.MemoryStorage" Name="MemoryStorage" />
      <Provider Type="Orleans.Storage.MemoryStorage" Name="PubSubStore" />
    </StorageProviders>
    <StreamProviders>
      <Provider Type="Orleans.Providers.Streams.SimpleMessageStream.SimpleMessageStreamProvider" Name="ActivityProvider" />
      <Provider Type="Vault.Activity.Streams.EventStoreStreamProvider" Name="EventStream" DataConnectionString="Server=127.0.01;Port=5432;Database=vault;User Id=postgres;Password=abc123!;Timeout=60" />
    </StreamProviders>
    <BootstrapProviders>
      <Provider Type="Vault.Activity.Host.Bootstrap" Name="Activity" />
    </BootstrapProviders>
    <Messaging>
      <SerializationProviders>
        <Provider type="Orleans.Serialization.BondSerializer, OrleansBondUtils"/>
      </SerializationProviders>
    </Messaging>
  </Globals>
  <Defaults>
    <Networking Address="localhost" Port="11111" />
    <ProxyingGateway Address="localhost" Port="30000" />
    <Startup Type="Vault.Activity.Host.Startup,Vault.Activity.Host" />
  </Defaults>
</OrleansConfiguration>